flexi_nlp_tools/__init__.py
flexi_nlp_tools/exceptions.py
flexi_nlp_tools/flexi_dict/__init__.py
flexi_nlp_tools/flexi_dict/config.py
flexi_nlp_tools/flexi_dict/exceptions.py
flexi_nlp_tools/flexi_dict/flexi_dict.py
flexi_nlp_tools/flexi_dict/utils.py
flexi_nlp_tools/flexi_dict/validators.py
flexi_nlp_tools/flexi_dict/flexi_trie/__init__.py
flexi_nlp_tools/flexi_dict/flexi_trie/flexi_trie.py
flexi_nlp_tools/flexi_dict/flexi_trie/flexi_trie_traverser.py
flexi_nlp_tools/flexi_dict/search_engine/__init__.py
flexi_nlp_tools/flexi_dict/search_engine/correction.py
flexi_nlp_tools/flexi_dict/search_engine/correction_detail.py
flexi_nlp_tools/flexi_dict/search_engine/fuzzy_search_result.py
flexi_nlp_tools/flexi_dict/search_engine/search_engine.py
flexi_nlp_tools/flexi_dict/search_engine/search_state.py
flexi_nlp_tools/lite_search/__init__.py
flexi_nlp_tools/lite_search/config.py
flexi_nlp_tools/lite_search/exceptions.py
flexi_nlp_tools/lite_search/fuzzy_searcher.py
flexi_nlp_tools/lite_search/index_builder.py
flexi_nlp_tools/lite_search/search_index.py
flexi_nlp_tools/lite_search/utils.py
flexi_nlp_tools/lite_translit/__init__.py
flexi_nlp_tools/lite_translit/lite_translit.py
flexi_nlp_tools/lite_translit/tokenizer.py
flexi_nlp_tools/numeral_converter/__init__.py
flexi_nlp_tools/numeral_converter/config.py
flexi_nlp_tools/numeral_converter/numeral_converter.py
flexi_nlp_tools/numeral_converter/numeral_converter_helpers.py
flexi_nlp_tools/numeral_converter/numeral_converter_loader.py
flexi_nlp_tools/numeral_converter/numeral_preprocessor.py
flexi_nlp_tools/numeral_converter/patterns.py
flexi_nlp_tools/numeral_converter/text.py
flexi_nlp_tools/numeral_converter/utils.py
flexi_nlp_tools/numeral_converter/numeral_data_collector/__init__.py
flexi_nlp_tools/numeral_converter/numeral_data_collector/numeral_data_cointainer.py
flexi_nlp_tools/numeral_converter/numeral_data_collector/numeral_data_collector.py
flexi_nlp_tools-0.6.0.dist-info/licenses/LICENSE
flexi_nlp_tools-0.6.0.dist-info/METADATA
flexi_nlp_tools-0.6.0.dist-info/WHEEL
flexi_nlp_tools-0.6.0.dist-info/top_level.txt
flexi_nlp_tools-0.6.0.dist-info/RECORD
