Metadata-Version: 2.4
Name: flexi-nlp-tools
Version: 0.6.0
Summary: NLP toolkit based on the flexi-dict data structure, designed for efficient fuzzy search, with a focus on simplicity, performance, and flexibility.
Author: Tetiana Lytvynenko
Author-email: lytvynenkotv@gmail.com
License: MIT
Keywords: fuzzy search,flexi search,nlp tools,natural language processing,text processing,string matching,phonetic matching,language tools,transliteration,transliterator,text conversion,numeral converter,text normalization,linguistic tools,rule-based transliteration
Classifier: Programming Language :: Python :: 3
Classifier: License :: OSI Approved :: MIT License
Classifier: Operating System :: OS Independent
Requires-Python: >=3.10
License-File: LICENSE
Requires-Dist: pandas<2.3,>=2.2.3
Dynamic: author
Dynamic: author-email
Dynamic: classifier
Dynamic: description
Dynamic: description-content-type
Dynamic: keywords
Dynamic: license
Dynamic: license-file
Dynamic: requires-dist
Dynamic: requires-python
Dynamic: summary
